rlc_chart.py
rlc_chart-1.0.0.dist-info/LICENSE
rlc_chart-1.0.0.dist-info/METADATA
rlc_chart-1.0.0.dist-info/WHEEL
rlc_chart-1.0.0.dist-info/top_level.txt
rlc_chart-1.0.0.dist-info/zip-safe
rlc_chart-1.0.0.dist-info/RECORD
