Metadata-Version: 2.1
Name: rlc-chart
Version: 1.0.0
Summary: A library that renders impedance charts that include capacitance and inductance grids.
Home-page: https://nurdletech.com/linux-utilities/rlc_chart
Author: Ken Kundert
Author-email: rlc_chart@nurdletech.com
License: GPLv3+
Download-URL: https://github.com/kenkundert/rlc_chart/tarball/master
Platform: UNKNOWN
Classifier: Development Status :: 5 - Production/Stable
Classifier: Intended Audience :: Science/Research
Classifier: License :: OSI Approved :: GNU General Public License v3 or later (GPLv3+)
Classifier: Natural Language :: English
Classifier: Operating System :: POSIX :: Linux
Classifier: Programming Language :: Python :: 3.6
Classifier: Programming Language :: Python :: 3.7
Classifier: Programming Language :: Python :: 3.8
Classifier: Programming Language :: Python :: 3.9
Classifier: Topic :: Utilities
Classifier: Topic :: Scientific/Engineering
Requires-Python: >=3.6
Requires-Dist: quantiphy
Requires-Dist: svgwrite
